setup.py
elasticsearch_util/__init__.py
elasticsearch_util/helper.py
elasticsearch_util.egg-info/PKG-INFO
elasticsearch_util.egg-info/SOURCES.txt
elasticsearch_util.egg-info/dependency_links.txt
elasticsearch_util.egg-info/requires.txt
elasticsearch_util.egg-info/top_level.txt
elasticsearch_util.egg-info/zip-safe