Metadata-Version: 1.0
Name: elasticsearch-util
Version: 0.1.0
Summary: Pythonic ElasticSearch Logging
Home-page: https://github.intel.com/gshaat/elasticsearch_util
Author: Gehad Shaat
Author-email: gehad.shaat@intel.com
License: MIT License
Keywords: kibana elasticsearch
Platform: UNKNOWN
